delinea/__init__.py
delinea/secrets/__init__.py
delinea/secrets/vault.py
python_dsv_sdk-1.0.4.dist-info/LICENSE
python_dsv_sdk-1.0.4.dist-info/WHEEL
python_dsv_sdk-1.0.4.dist-info/METADATA
python_dsv_sdk-1.0.4.dist-info/RECORD
