Metadata-Version: 2.1
Name: python-dsv-sdk
Version: 1.0.4
Summary: The Delinea DevOps Secret Vault Python SDK
Author: Delinea
Requires-Python: >=3.7
Classifier: License :: OSI Approved :: Apache Software License
Classifier: Operating System :: OS Independent
Classifier: Programming Language :: Python :: 3.7
Classifier: Programming Language :: Python :: 3.8
Classifier: Programming Language :: Python :: 3.9
Classifier: Programming Language :: Python :: 3.10
Requires-Dist: requests >= 2.22.0
